cruxgen_sdk/sdk.py
cruxgen_sdk-0.1.1.dist-info/METADATA
cruxgen_sdk-0.1.1.dist-info/WHEEL
cruxgen_sdk-0.1.1.dist-info/top_level.txt
cruxgen_sdk-0.1.1.dist-info/RECORD
