Metadata-Version: 2.4
Name: cruxgen-sdk
Version: 0.1.1
Summary: Call CruxGen Server APIs with ease.
Requires-Python: >=3.11
Requires-Dist: httpx>=0.28.1
Requires-Dist: orjson>=3.11.3
